wink_sdk_extranet_monetize/__init__.py
wink_sdk_extranet_monetize/api_client.py
wink_sdk_extranet_monetize/api_response.py
wink_sdk_extranet_monetize/configuration.py
wink_sdk_extranet_monetize/exceptions.py
wink_sdk_extranet_monetize/py.typed
wink_sdk_extranet_monetize/rest.py
wink_sdk_extranet_monetize/api/__init__.py
wink_sdk_extranet_monetize/api/add_on_api.py
wink_sdk_extranet_monetize/api/cancellation_policy_api.py
wink_sdk_extranet_monetize/api/daily_rate_api.py
wink_sdk_extranet_monetize/api/inventory_api.py
wink_sdk_extranet_monetize/api/inventory_usage_api.py
wink_sdk_extranet_monetize/api/master_rate_api.py
wink_sdk_extranet_monetize/api/promotion_api.py
wink_sdk_extranet_monetize/api/promotion_bundle_api.py
wink_sdk_extranet_monetize/api/rate_plan_api.py
wink_sdk_extranet_monetize/models/__init__.py
wink_sdk_extranet_monetize/models/add_on.py
wink_sdk_extranet_monetize/models/address.py
wink_sdk_extranet_monetize/models/address_supplier.py
wink_sdk_extranet_monetize/models/advance_booking_rate_qualifier_supplier.py
wink_sdk_extranet_monetize/models/aggregate_descriptor_supplier.py
wink_sdk_extranet_monetize/models/arrival_days_of_week_rate_qualifier_supplier.py
wink_sdk_extranet_monetize/models/available_days_of_week_rate_qualifier_supplier.py
wink_sdk_extranet_monetize/models/bed_supplier.py
wink_sdk_extranet_monetize/models/bedroom_configuration_supplier.py
wink_sdk_extranet_monetize/models/bedroom_supplier.py
wink_sdk_extranet_monetize/models/blackout_date_supplier.py
wink_sdk_extranet_monetize/models/cancellation_policy.py
wink_sdk_extranet_monetize/models/cancellation_policy_exception.py
wink_sdk_extranet_monetize/models/cancellation_policy_exception_supplier.py
wink_sdk_extranet_monetize/models/cancellation_policy_exceptions.py
wink_sdk_extranet_monetize/models/cancellation_policy_exceptions_supplier.py
wink_sdk_extranet_monetize/models/cancellation_policy_lightweight.py
wink_sdk_extranet_monetize/models/cancellation_policy_lightweight_supplier.py
wink_sdk_extranet_monetize-0.0.57.dist-info/licenses/LICENSE
wink_sdk_extranet_monetize-0.0.57.dist-info/METADATA
wink_sdk_extranet_monetize-0.0.57.dist-info/WHEEL
wink_sdk_extranet_monetize-0.0.57.dist-info/top_level.txt
wink_sdk_extranet_monetize-0.0.57.dist-info/RECORD
